1st_semester/Estructura de computadores/P2/alu.v
module alu(output reg [7:0] S,    // Salida de la ALU
           output reg zero,       // Flag de cero
           input wire [7:0] A, B, // Operandos
           input wire [2:0] Op    // Elección de operación a realizar
           );
// Una ALU simple que puede realizar 8 operaciones diferentes, y que devuelve el resultado, además de flags de cero y acarreo
	   
always @(A, B, Op)
begin
  case (Op)              
    3'b000: S = A; 
    3'b001: S = ~A;
    3'b010: S = A + B;
    3'b011: S = A - B;
    3'b100: S = A & B;
    3'b101: S = A | B;
    3'b110: S = -A;
    3'b111: S = -B;
	  default: S = 'bx; //desconocido en cualquier otro caso (x | z), por si se modifica el código
  endcase
  //Calculo del flag de cero
  zero = ~(|S);   //operador de reducción |y hace la or de los bits del vector 'y' y devuelve 1 bit resultado
end
	   
endmodule

1st_semester/Estructura de computadores/P2/memprog.v
//Memoria de programa, se inicializa y no se modifica

module memprog(output wire [15:0] Data,     // Dato que se lee de memoria
               input  wire clk,             // Señal de reloj
               input  wire [9:0] Address);  // Dirección de memoria a la que se accede

  reg [15:0] Mem[0:1023]; //memoria de 1024 palabras de 16 bits de ancho

  initial
  begin
    $readmemb("progfile.dat", Mem); // inicializa la memoria del fichero en texto binario
  end
  assign Data = Mem[Address];
endmodule

1st_semester/Estructura de computadores/P2/microc.v
module microc(output wire [5:0] Opcode, output wire z, input wire clk, reset, s_inc, s_inm, we3, s_skip, input wire [2:0] Op);
//Microcontrolador sin memoria de datos de un solo ciclo
wire [7:0] rd1, rd2, wd3, alu_out, inm;    
wire [15:0] instruccion;
wire [9:0] pc_out, pc_in, dir_salto, mux_out, sum_out;

assign dir_salto = instruccion[9:0];

memprog memoria(instruccion, clk, pc_out);

registro #(10) PC(pc_out, clk, reset, pc_in);

regfile Banco_reg(rd1, rd2, clk, we3, instruccion[3:0], instruccion[7:4], instruccion[11:8], wd3);

alu ALU(alu_out, z, rd1, rd2, Op);

// Mux de la izq del todo
mux2 #(10) mux1(pc_in, dir_salto, sum_out, s_inc);

// Mux del centro
assign n1 = 10'b0000000001;
assign n2 = 10'b0000000010;
mux2 #(10) mux2(mux_out, n1, n2, s_skip);

// Mux de la derecha
assign inm = instruccion[11:4];
mux2 #(10) mux3(wd3, alu_out, inm, s_inm);

sum sumador(sum_out, mux_out, pc_out);

assign OPCODE = instruccion[15:10];

endmodule

1st_semester/Estructura de computadores/P2/microc_tb.v
`timescale 1 ns / 10 ps
module microc_tb;

// Declaración de variables
reg clk, reset, s_inc, s_inm, we3, s_skip;
reg [2:0] Op;
wire z;
wire [5:0] Opcode;

// Instanciación del camino de datos
microc micro(Opcode, z, clk, reset, s_inc, s_inm, we3, s_skip, Op);

// Generación de reloj clk
always
begin
  clk=1;
  #10;
  clk=0;
  #10;
end

// Reseteo y configuración de salidas del testbench
initial
begin
  $dumpfile("microc_tb.vcd");
  $dumpvars;
  
  //integer idx;
  //$dumpvars(0,  .br.R[1])

  reset = 1;  
  #5  
  reset = 0;

end

// Bloque simulación señales control por ciclo
initial
begin
  // Ciclo 1 (li 0, R1)
  #10   
  s_inc = 1;
  s_skip = 0;
  we3 = 1;
  Op = 3'b000;
  s_inm = 1;

  // Ciclo 2 (li 1, R2)
  #20 
  s_inc = 1;
  s_skip = 0;
  we3 = 1;
  Op = 3'b000;
  s_inm = 1; 

  // Ciclo 3 (li 4, R3)
  #20 
  s_inc = 1;
  s_skip = 0;
  we3 = 1;
  Op = 3'b000;
  s_inm = 1;

  // Ciclo 4 (li 0, R4)
  #20 
  s_inc = 1;
  s_skip = 0;
  we3 = 1;
  Op = 3'b000;
  s_inm = 1;

  // Ciclo 5 (and R3, R2, R5)(Bucle: )
  #20
  s_inc = 1;
  s_skip = 0;
  we3 = 1;
  Op = 3'b100;
  s_inm = 0; 

  // Ciclo 6 (skipne R5, R4)
  #20
  s_inc = 1;
  s_skip = 0;
  we3 = 1;
  Op = 3'b011;
  s_inm = 0;

  // Ciclo 7 (add R1, R2, R1)
  #20
  s_inc = 1;
  s_skip = 0;
  we3 = 1;
  Op = 3'b010;
  s_inm = 0; 

  // Ciclo 8 (sub R3, R2, R3)
  #20
  s_inc = 1;
  s_skip = 0;
  we3 = 1;
  Op = 3'b011;
  s_inm = 0; 

  // Ciclo 9 (skipeq R3, R2)
  #20
  s_inc = 1;
  s_skip = 0;
  we3 = 0;
  Op = 3'b011;
  s_inm = 0;

  // Ciclo 10 (j Bucle)
  #20
  s_inc = 0;
  s_skip = 0;
  we3 = 0;
  Op = 3'b000;
  s_inm = 0; 

  // Ciclo 11 (and R3, R2, R5)(Bucle: )
  #20
  s_inc = 1;
  s_skip = 0;
  we3 = 1;
  Op = 3'b100;
  s_inm = 0; 

  // Ciclo 12 (skpine R5, R4)
  #20 
  s_inc = 1;
  s_skip = 0;
  we3 = 1;
  Op = 3'b011;
  s_inm = 0;

  // Ciclo 13 (add R1, R2, R1)
  #20 
  s_inc = 1;
  s_skip = 0;
  we3 = 1;
  Op = 3'b010;
  s_inm = 0;

  // Ciclo 14 (sub R3, R2, R3)
  #20 
  s_inc = 1;
  s_skip = 0;
  we3 = 1;
  Op = 3'b011;
  s_inm = 0;

  // Ciclo 15 (skipeq R3, R2)
  #20 
  s_inc = 1;
  s_skip = 0;
  we3 = 0;
  Op = 3'b011;
  s_inm = 0;

  // Ciclo 16 (j Bucle)
  #20 
  s_inc = 0;
  s_skip = 0;
  we3 = 0;
  Op = 3'b000;
  s_inm = 0;

  // Ciclo 17 (and R3, R2, R5)(Bucle: )
  #20 
  s_inc = 1;
  s_skip = 0;
  we3 = 1;
  Op = 3'b100;
  s_inm = 0;

  // Ciclo 18 (skipne R5, R4)
  #20  
  s_inc = 1;
  s_skip = 0;
  we3 = 0;
  Op = 3'b011;
  s_inm = 0;

  // Ciclo 19 (add R1, R2, R1)
  #20 
  s_inc = 1;
  s_skip = 0;
  we3 = 1;
  Op = 3'b010;
  s_inm = 0;

  // Ciclo 20 (sub R3, R2, R3)
  #20 
  s_inc = 1;
  s_skip = 0;
  we3 = 1;
  Op = 3'b011;
  s_inm = 0;

  // Ciclo 21 (skipeq R3, R2)
  #20 
  s_inc = 1;
  s_skip = 1;
  we3 = 0;
  Op = 3'b011;
  s_inm = 0;

  // Ciclo 22 (j Fin)
  #20 
  s_inc = 0;
  s_skip = 0;
  we3 = 0;
  Op = 3'b000;
  s_inm = 0;

  // Ciclo 23 (j Fin)
  #20 
  s_inc = 0;
  s_skip = 0;
  we3 = 0;
  Op = 3'b000;
  s_inm = 0;;

  $finish;
end

endmodule

1st_semester/Estructura_de_Computadores/SEGUNDA_PRACTICA/componentes.v
//Componentes varios

// Banco de registros de dos salidas y una entrada
module regfile(output wire [7:0]  RD1, RD2,     //datos leidos
               input  wire        clk,          // Señal de reloj
               input  wire        we3,          //señal de habilitación de escritura
               input  wire [3:0]  RA1, RA2, WA3,//direcciones de regs leidos y reg a escribir
               input  wire [7:0]  WD3);         //dato a escribir

  reg [7:0] R[0:15]; //memoria de 32 registros de 8 bits de ancho

  initial
  begin
    $readmemb("regfile.dat",R); // inicializa los registros a valores conocidos
  end  
  
  // El registro 0 siempre es cero
  // se leen dos reg combinacionalmente
  // y la escritura del tercero ocurre en flanco de subida del reloj
  always @(posedge clk)
    if (we3) R[WA3] <= WD3;	
  
  assign RD1 = (RA1 != 0) ? R[RA1] : 0;
  assign RD2 = (RA2 != 0) ? R[RA2] : 0;
endmodule

// Sumador simple
module sum(output wire [9:0] Y,     // Salida del sumador
           input  wire [9:0] A, B); // Operandos de la suma

  assign Y = A + B;
endmodule

// Registro de tamaño configurable para modelar el PC. Cambia en cada flanco de subida de reloj o de reset
module registro #(parameter WIDTH = 8)
              (output reg  [WIDTH-1:0] Q,           // Salida del registro
               input  wire             clk, reset,  // Señales de reloj y reseteo
               input  wire [WIDTH-1:0] D);          // Entrada al registro

  always @(posedge clk, posedge reset)
    if (reset) Q <= 0;
    else       Q <= D;
endmodule

// Multiplexor de dos entradas y una salida, de tamaño configurable. Si la señal de selección "s" vale 1, se pone el valor de d1 en la salida; d0 si vale 0
module mux2 #(parameter WIDTH = 8)
             (output wire [WIDTH-1:0] Y,      // Salida del multiplexor
              input  wire [WIDTH-1:0] D0, D1, // Entradas del multiplexor
              input  wire             s);     // Selección

  assign Y = s ? D1 : D0; 
endmodule

//Biestable para el flag de cero
//Biestable tipo D síncrono con reset asíncrono por flanco y entrada de habilitación de carga
module ffd(input wire clk, reset, d, carga, output reg q);
  always @(posedge clk, posedge reset)
    if (reset)
	    q <= 1'b0;
	  else
	    if (carga)
	      q <= d;
endmodule

1st_semester/Estructura de computadores/P2/microc_tb.vcd
$date
	Thu Nov 21 12:58:33 2024
$end
$version
	Icarus Verilog
$end
$timescale
	10ps
$end
$scope module ffd $end
$var wire 1 ! carga $end
$var wire 1 " clk $end
$var wire 1 # d $end
$var wire 1 $ reset $end
$var reg 1 % q $end
$upscope $end
$scope module microc_tb $end
$var wire 6 & Opcode [5:0] $end
$var wire 1 ' z $end
$var reg 3 ( Op [2:0] $end
$var reg 1 ) clk $end
$var reg 1 * reset $end
$var reg 1 + s_inc $end
$var reg 1 , s_inm $end
$var reg 1 - s_skip $end
$var reg 1 . we3 $end
$scope module micro $end
$var wire 3 / Op [2:0] $end
$var wire 6 0 Opcode [5:0] $end
$var wire 1 ) clk $end
$var wire 1 1 n1 $end
$var wire 1 2 n2 $end
$var wire 1 * reset $end
$var wire 1 + s_inc $end
$var wire 1 , s_inm $end
$var wire 1 - s_skip $end
$var wire 1 . we3 $end
$var wire 1 ' z $end
$var wire 8 3 wd3 [7:0] $end
$var wire 10 4 sum_out [9:0] $end
$var wire 8 5 rd2 [7:0] $end
$var wire 8 6 rd1 [7:0] $end
$var wire 10 7 pc_out [9:0] $end
$var wire 10 8 pc_in [9:0] $end
$var wire 10 9 mux_out [9:0] $end
$var wire 16 : instruccion [15:0] $end
$var wire 8 ; inm [7:0] $end
$var wire 10 < dir_salto [9:0] $end
$var wire 8 = alu_out [7:0] $end
$var wire 1 > OPCODE $end
$scope module ALU $end
$var wire 3 ? Op [2:0] $end
$var wire 8 @ B [7:0] $end
$var wire 8 A A [7:0] $end
$var reg 8 B S [7:0] $end
$var reg 1 ' zero $end
$upscope $end
$scope module Banco_reg $end
$var wire 4 C RA1 [3:0] $end
$var wire 4 D RA2 [3:0] $end
$var wire 4 E WA3 [3:0] $end
$var wire 8 F WD3 [7:0] $end
$var wire 1 ) clk $end
$var wire 1 . we3 $end
$var wire 8 G RD2 [7:0] $end
$var wire 8 H RD1 [7:0] $end
$upscope $end
$scope module PC $end
$var wire 1 ) clk $end
$var wire 1 * reset $end
$var wire 10 I D [9:0] $end
$var reg 10 J Q [9:0] $end
$upscope $end
$scope module memoria $end
$var wire 10 K Address [9:0] $end
$var wire 16 L Data [15:0] $end
$var wire 1 ) clk $end
$upscope $end
$scope module mux1 $end
$var wire 10 M D0 [9:0] $end
$var wire 1 + s $end
$var wire 10 N Y [9:0] $end
$var wire 10 O D1 [9:0] $end
$upscope $end
$scope module mux2 $end
$var wire 10 P D0 [9:0] $end
$var wire 10 Q D1 [9:0] $end
$var wire 1 - s $end
$var wire 10 R Y [9:0] $end
$upscope $end
$scope module mux3 $end
$var wire 10 S D0 [9:0] $end
$var wire 10 T D1 [9:0] $end
$var wire 1 , s $end
$var wire 10 U Y [9:0] $end
$upscope $end
$scope module sumador $end
$var wire 10 V A [9:0] $end
$var wire 10 W B [9:0] $end
$var wire 10 X Y [9:0] $end
$upscope $end
$upscope $end
$upscope $end
$enddefinitions $end
#0
$dumpvars
bx X
b0 W
b0x V
b0xxxxxxxx U
b0 T
b0xxxxxxxx S
b0x R
b0 Q
b1 P
bx O
bx N
b1 M
b1000000000001 L
b0 K
b0 J
bx I
b0 H
b0 G
bx F
b0 E
b0 D
b1 C
bx B
b0 A
b0 @
bx ?
0>
bx =
b1 <
b0 ;
b1000000000001 :
b0x 9
bx 8
b0 7
b0 6
b0 5
bx 4
bx 3
02
11
bz 0
bx /
x.
x-
x,
x+
1*
1)
bx (
x'
bz &
x%
z$
z#
z"
z!
$end
#500
0*
#1000
b0 3
b0 F
b1 8
b1 I
b1 N
b0 U
1'
b0 S
b0 =
b0 B
b1 4
b1 O
b1 X
b1 9
b1 R
b1 V
1,
b0 (
b0 /
b0 ?
1.
0-
1+
0)
#2000
b1 3
b1 F
b1 U
b1 T
b1 ;
b1 D
b10 C
b10010 <
b10010 M
b10 8
b10 I
b10 N
b1000000010010 :
b1000000010010 L
b10 4
b10 O
b10 X
b1 7
b1 J
b1 K
b1 W
1)
#3000
0)
#4000
b100 3
b100 F
b100 U
b100 T
b100 ;
b100 D
b11 C
b1000011 <
b1000011 M
b11 8
b11 I
b11 N
b1000001000011 :
b1000001000011 L
b11 4
b11 O
b11 X
b10 7
b10 J
b10 K
b10 W
1)
#5000
0)
#6000
b0 3
b0 F
b0 U
b0 T
b0 ;
b0 D
b100 C
b100 <
b100 M
b100 8
b100 I
b100 N
b1000000000100 :
b1000000000100 L
b100 4
b100 O
b100 X
b11 7
b11 J
b11 K
b11 W
1)
#7000
0)
#8000
b110010 3
b110010 F
b110010 U
b110010 T
b110010 ;
b11 E
b10 D
b101 C
b1100100101 <
b1100100101 M
b101 8
b101 I
b101 N
b1100001100100101 :
b1100001100100101 L
b101 4
b101 O
b101 X
b100 7
b100 J
b100 K
b100 W
1)
#9000
b0 3
b0 F
b0 U
0)
0,
b100 (
b100 /
b100 ?
#10000
1>
b1010100 T
b1010100 ;
b101 E
b100 D
b1 C
b101000001 <
b101000001 M
b110 8
b110 I
b110 N
b100010101000001 :
b100010101000001 L
b110 4
b110 O
b110 X
b101 7
b101 J
b101 K
b101 W
1)
#11000
0)
b11 (
b11 /
b11 ?
#12000
0>
b10010 T
b10010 ;
b1 E
b10 D
b100100001 <
b100100001 M
b111 8
b111 I
b111 N
b1010000100100001 :
b1010000100100001 L
b111 4
b111 O
b111 X
b110 7
b110 J
b110 K
b110 W
1)
#13000
0)
b10 (
b10 /
b10 ?
#14000
b110010 T
b110010 ;
b11 E
b11 C
b1100100011 <
b1100100011 M
b1000 8
b1000 I
b1000 N
b1011001100100011 :
b1011001100100011 L
b1000 4
b1000 O
b1000 X
b111 7
b111 J
b111 K
b111 W
1)
#15000
0)
b11 (
b11 /
b11 ?
#16000
b1 C
b1100100001 <
b1100100001 M
b1001 8
b1001 I
b1001 N
b11001100100001 :
b11001100100001 L
b1001 4
b1001 O
b1001 X
b1000 7
b1000 J
b1000 K
b1000 W
1)
#17000
0)
0.
#18000
b0 T
b0 ;
b0 E
b0 D
b100 C
b100 <
b100 M
b1010 8
b1010 I
b1010 N
b10000000000100 :
b10000000000100 L
b1010 4
b1010 O
b1010 X
b1001 7
b1001 J
b1001 K
b1001 W
1)
#19000
b100 8
b100 I
b100 N
0)
b0 (
b0 /
b0 ?
0+
#20000
b1100100101 8
b1100100101 I
b1100100101 N
b110010 T
b110010 ;
b11 E
b10 D
b101 C
b1100100101 <
b1100100101 M
b1100001100100101 :
b1100001100100101 L
b101 4
b101 O
b101 X
b100 7
b100 J
b100 K
b100 W
1)
#21000
b101 8
b101 I
b101 N
0)
b100 (
b100 /
b100 ?
1.
1+
#22000
1>
b1010100 T
b1010100 ;
b101 E
b100 D
b1 C
b101000001 <
b101000001 M
b110 8
b110 I
b110 N
b100010101000001 :
b100010101000001 L
b110 4
b110 O
b110 X
b101 7
b101 J
b101 K
b101 W
1)
#23000
0)
b11 (
b11 /
b11 ?
#24000
0>
b10010 T
b10010 ;
b1 E
b10 D
b100100001 <
b100100001 M
b111 8
b111 I
b111 N
b1010000100100001 :
b1010000100100001 L
b111 4
b111 O
b111 X
b110 7
b110 J
b110 K
b110 W
1)
#25000
0)
b10 (
b10 /
b10 ?
#26000
b110010 T
b110010 ;
b11 E
b11 C
b1100100011 <
b1100100011 M
b1000 8
b1000 I
b1000 N
b1011001100100011 :
b1011001100100011 L
b1000 4
b1000 O
b1000 X
b111 7
b111 J
b111 K
b111 W
1)
#27000
0)
b11 (
b11 /
b11 ?
#28000
b1 C
b1100100001 <
b1100100001 M
b1001 8
b1001 I
b1001 N
b11001100100001 :
b11001100100001 L
b1001 4
b1001 O
b1001 X
b1000 7
b1000 J
b1000 K
b1000 W
1)
#29000
0)
0.
#30000
b0 T
b0 ;
b0 E
b0 D
b100 C
b100 <
b100 M
b1010 8
b1010 I
b1010 N
b10000000000100 :
b10000000000100 L
b1010 4
b1010 O
b1010 X
b1001 7
b1001 J
b1001 K
b1001 W
1)
#31000
b100 8
b100 I
b100 N
0)
b0 (
b0 /
b0 ?
0+
#32000
b1100100101 8
b1100100101 I
b1100100101 N
b110010 T
b110010 ;
b11 E
b10 D
b101 C
b1100100101 <
b1100100101 M
b1100001100100101 :
b1100001100100101 L
b101 4
b101 O
b101 X
b100 7
b100 J
b100 K
b100 W
1)
#33000
b101 8
b101 I
b101 N
0)
b100 (
b100 /
b100 ?
1.
1+
#34000
1>
b1010100 T
b1010100 ;
b101 E
b100 D
b1 C
b101000001 <
b101000001 M
b110 8
b110 I
b110 N
b100010101000001 :
b100010101000001 L
b110 4
b110 O
b110 X
b101 7
b101 J
b101 K
b101 W
1)
#35000
0)
b11 (
b11 /
b11 ?
0.
#36000
0>
b10010 T
b10010 ;
b1 E
b10 D
b100100001 <
b100100001 M
b111 8
b111 I
b111 N
b1010000100100001 :
b1010000100100001 L
b111 4
b111 O
b111 X
b110 7
b110 J
b110 K
b110 W
1)
#37000
0)
b10 (
b10 /
b10 ?
1.
#38000
b110010 T
b110010 ;
b11 E
b11 C
b1100100011 <
b1100100011 M
b1000 8
b1000 I
b1000 N
b1011001100100011 :
b1011001100100011 L
b1000 4
b1000 O
b1000 X
b111 7
b111 J
b111 K
b111 W
1)
#39000
0)
b11 (
b11 /
b11 ?
#40000
b1 C
b1100100001 <
b1100100001 M
b1001 8
b1001 I
b1001 N
b11001100100001 :
b11001100100001 L
b1001 4
b1001 O
b1001 X
b1000 7
b1000 J
b1000 K
b1000 W
1)
#41000
b1000 8
b1000 I
b1000 N
b1000 4
b1000 O
b1000 X
b0 9
b0 R
b0 V
0)
0.
1-
#42000
1)
#43000
b1001 4
b1001 O
b1001 X
b1 9
b1 R
b1 V
b1100100001 8
b1100100001 I
b1100100001 N
0)
b0 (
b0 /
b0 ?
0-
0+
#44000
b0 8
b0 I
b0 N
b0 T
b0 ;
b0 E
b0 D
b0 C
b0 <
b0 M
b0 :
b0 L
b1100100010 4
b1100100010 O
b1100100010 X
b1100100001 7
b1100100001 J
b1100100001 K
b1100100001 W
1)
